pybsuir/__init__.py
pybsuir/client.py
pybsuir/interafces.py
pybsuir/exceptions/__init__.py
pybsuir/exceptions/exceptions.py
pybsuir/exceptions/exceptions_utils.py
pybsuir/types/__init__.py
pybsuir/types/groups.py
pybsuir/types/types.py
pybsuir/utils/__init__.py
pybsuir/utils/dict_utils.py
pybsuir/utils/http_utils.py
pybsuir-0.0.1b0.dist-info/licenses/LICENSE
pybsuir-0.0.1b0.dist-info/METADATA
pybsuir-0.0.1b0.dist-info/WHEEL
pybsuir-0.0.1b0.dist-info/top_level.txt
pybsuir-0.0.1b0.dist-info/RECORD
