Metadata-Version: 2.4
Name: pybsuir
Version: 0.0.1b0
Summary: Взаимедействие с API БГУИР
Author-email: boykopovar <boykopovar@gmail.com>
License-Expression: MIT
Requires-Python: >=3.8
License-File: LICENSE
Requires-Dist: aiohttp
Dynamic: license-file
